confluent_flink_table_api_python_plugin-1.20.56.data/scripts/find-flink-home.sh
confluent_flink_table_api_python_plugin-1.20.56.data/scripts/find_flink_home.py
confluent_flink_table_api_python_plugin-1.20.56.data/scripts/pyflink-shell.sh
pyflink/__init__.py
pyflink/find_flink_home.py
pyflink/gen_protos.py
pyflink/java_gateway.py
pyflink/pyflink_callback_server.py
pyflink/pyflink_gateway_server.py
pyflink/serializers.py
pyflink/shell.py
pyflink/version.py
pyflink/bin/find-flink-home.sh
pyflink/bin/pyflink-shell.sh
pyflink/common/__init__.py
pyflink/common/completable_future.py
pyflink/common/config_options.py
pyflink/common/configuration.py
pyflink/common/constants.py
pyflink/common/execution_config.py
pyflink/common/execution_mode.py
pyflink/common/input_dependency_constraint.py
pyflink/common/io.py
pyflink/common/job_client.py
pyflink/common/job_execution_result.py
pyflink/common/job_id.py
pyflink/common/job_status.py
pyflink/common/restart_strategy.py
pyflink/common/serialization.py
pyflink/common/serializer.py
pyflink/common/time.py
pyflink/common/typeinfo.py
pyflink/common/types.py
pyflink/common/utils.py
pyflink/common/watermark_strategy.py
pyflink/datastream/__init__.py
pyflink/datastream/checkpoint_config.py
pyflink/datastream/checkpoint_storage.py
pyflink/datastream/checkpointing_mode.py
pyflink/datastream/data_stream.py
pyflink/datastream/execution_mode.py
pyflink/datastream/externalized_checkpoint_retention.py
pyflink/datastream/functions.py
pyflink/datastream/output_tag.py
pyflink/datastream/slot_sharing_group.py
pyflink/datastream/state.py
pyflink/datastream/state_backend.py
pyflink/datastream/stream_execution_environment.py
pyflink/datastream/time_characteristic.py
pyflink/datastream/time_domain.py
pyflink/datastream/timerservice.py
pyflink/datastream/utils.py
pyflink/datastream/window.py
pyflink/datastream/connectors/__init__.py
pyflink/datastream/connectors/base.py
pyflink/datastream/connectors/cassandra.py
confluent_flink_table_api_python_plugin-1.20.56.dist-info/METADATA
confluent_flink_table_api_python_plugin-1.20.56.dist-info/WHEEL
confluent_flink_table_api_python_plugin-1.20.56.dist-info/top_level.txt
confluent_flink_table_api_python_plugin-1.20.56.dist-info/RECORD
