Metadata-Version: 2.4
Name: confluent-flink-table-api-python-plugin
Version: 1.20.56
Summary: Confluent Apache Flink Table API Python
Home-page: https://confluent.io
Author: Confluent
Author-email: dev@confluent.io
License: https://www.apache.org/licenses/LICENSE-2.0
Classifier: Development Status :: 5 - Production/Stable
Classifier: Programming Language :: Python :: 3.9
Classifier: Programming Language :: Python :: 3.10
Classifier: Programming Language :: Python :: 3.11
Requires-Python: >=3.8
Requires-Dist: py4j==0.10.9.7
Requires-Dist: python-dateutil<3,>=2.8.0
Requires-Dist: cloudpickle>=2.2.0
Requires-Dist: pytz>=2018.3
Requires-Dist: requests>=2.26.0
Requires-Dist: pemja==0.4.1; platform_system != "Windows"
Requires-Dist: httplib2>=0.19.0
Requires-Dist: ruamel.yaml>=0.18.4
Requires-Dist: confluent-flink-jars<1.20.57,>=1.20.56
Dynamic: author
Dynamic: author-email
Dynamic: classifier
Dynamic: description
Dynamic: description-content-type
Dynamic: home-page
Dynamic: license
Dynamic: requires-dist
Dynamic: requires-python
Dynamic: summary
